marshmallow_attrs/__init__.py
marshmallow_dataclass/__init__.py
marshmallow_dataclass/py.typed
marshmallow_attrs-0.1.1.dist-info/AUTHORS.rst
marshmallow_attrs-0.1.1.dist-info/LICENSE
marshmallow_attrs-0.1.1.dist-info/METADATA
marshmallow_attrs-0.1.1.dist-info/WHEEL
marshmallow_attrs-0.1.1.dist-info/top_level.txt
marshmallow_attrs-0.1.1.dist-info/RECORD
