Metadata-Version: 2.1
Name: marshmallow-attrs
Version: 0.1.1
Summary: Marshmallow schemas for attrs classes
Home-page: https://github.com/adamboche/marshmallow-attrs
Author: Adam Boche
Author-email: adamboche@users.noreply.github.com
License: UNKNOWN
Platform: UNKNOWN
Classifier: Development Status :: 3 - Alpha
Classifier: Intended Audience :: Developers
Classifier: License :: OSI Approved :: MIT License
Classifier: Operating System :: Unix
Classifier: Operating System :: POSIX
Classifier: Operating System :: Microsoft :: Windows
Classifier: Programming Language :: Python
Classifier: Programming Language :: Python :: 3
Classifier: Programming Language :: Python :: 3.6
Classifier: Programming Language :: Python :: 3.7
Classifier: Programming Language :: Python :: Implementation :: CPython
Classifier: Programming Language :: Python :: Implementation :: PyPy
Classifier: Topic :: Utilities
Requires-Dist: marshmallow
Requires-Dist: attrs
Requires-Dist: typing-inspect
Requires-Dist: marshmallow-enum
